qndiag/__init__.py
qndiag/pham.py
qndiag/qndiag.py
qndiag-0.1.dist-info/LICENSE
qndiag-0.1.dist-info/METADATA
qndiag-0.1.dist-info/WHEEL
qndiag-0.1.dist-info/top_level.txt
qndiag-0.1.dist-info/RECORD
