Metadata-Version: 2.1
Name: qndiag
Version: 0.1
Summary: Joint diagonalization in Python
Home-page: https://github.com/pierreablin/qndiag
Maintainer: Pierre Ablin
Maintainer-email: pierreablin@gmail.com
License: MIT
Download-URL: https://github.com/pierreablin/qndiag.git
Platform: any
Classifier: Intended Audience :: Science/Research
Classifier: Intended Audience :: Developers
Classifier: License :: OSI Approved
Classifier: Programming Language :: Python
Classifier: Topic :: Software Development
Classifier: Topic :: Scientific/Engineering
Classifier: Operating System :: Microsoft :: Windows
Classifier: Operating System :: POSIX
Classifier: Operating System :: Unix
Classifier: Operating System :: MacOS
